wordlistknife/__init__.py
wordlistknife/builder.py
wordlistknife/config.py
wordlistknife/input.py
wordlistknife/main.py
wordlistknife/mangle.py
wordlist_knife-0.0.2.dist-info/LICENSE
wordlist_knife-0.0.2.dist-info/METADATA
wordlist_knife-0.0.2.dist-info/WHEEL
wordlist_knife-0.0.2.dist-info/entry_points.txt
wordlist_knife-0.0.2.dist-info/top_level.txt
wordlist_knife-0.0.2.dist-info/RECORD
