Metadata-Version: 2.1
Name: wordlist-knife
Version: 0.0.2
Summary: Tool to mutate wordlists.
Home-page: https://github.com/kazkansouh/wordlist-knife
Author: Karim Kanso
Author-email: kaz.kanso@gmail.com
License: UNKNOWN
Platform: UNKNOWN
Classifier: Programming Language :: Python :: 3
Classifier: License :: OSI Approved :: GNU General Public License v3 (GPLv3)
Classifier: Operating System :: OS Independent
Classifier: Topic :: Security
